DOCUMENTATION.md
LICENSE
bvista/__init__.py
bvista/notebook_integration.py
bvista/server_manager.py
bvista/backend/__init__.py
bvista/backend/app.py
bvista/backend/config.py
bvista/backend/models/Missing_Data_Diagnostics.py
bvista/backend/models/correlation.py
bvista/backend/models/data_cleaning.py
bvista/backend/models/data_manager.py
bvista/backend/models/descriptive_stats.py
bvista/backend/models/distribution_analysis.py
bvista/backend/models/missing_data_analysis.py
bvista/backend/routes/data_routes.py
bvista/backend/static/config.py
bvista/backend/static/file_handler.py
bvista/backend/utils/helpers.py
bvista/backend/utils/logger.py
bvista/backend/websocket/__init__.py
bvista/backend/websocket/event_handlers.py
bvista/backend/websocket/socket_manager.py
bvista/datasets/__init__.py
bvista/datasets/ames_housing.csv
bvista/datasets/ames_housing.py
bvista/datasets/covid19_live.py
bvista/datasets/stock_prices.py
bvista/datasets/testing_data.csv
bvista/datasets/testing_data.py
bvista/datasets/titanic.csv
bvista/datasets/titanic.py
bvista/frontend/.gitignore
bvista/frontend/README.md
bvista/frontend/package-lock.json
bvista/frontend/package.json
bvista/frontend/public/favicon.ico
bvista/frontend/public/index.html
bvista/frontend/public/logo192.png
bvista/frontend/public/logo512.png
bvista/frontend/public/manifest.json
bvista/frontend/public/robots.txt
bvista/frontend/src/App.css
bvista/frontend/src/App.js
bvista/frontend/src/App.test.js
bvista/frontend/src/index.css
bvista/frontend/src/index.js
bvista/frontend/src/logo.svg
bvista/frontend/src/reportWebVitals.js
bvista/frontend/src/setupTests.js
bvista/frontend/src/components/CellEditor.js
bvista/frontend/src/components/Layout.css
bvista/frontend/src/components/Layout.js
bvista/frontend/src/components/Sidebar.css
bvista/frontend/src/components/Sidebar.js
bvista/frontend/src/pages/CorrelationMatrix.css
bvista/frontend/src/pages/CorrelationMatrix.js
bvista/frontend/src/pages/CustomHeader.js
bvista-1.1.1.dist-info/METADATA
bvista-1.1.1.dist-info/WHEEL
bvista-1.1.1.dist-info/licenses/LICENSE
bvista-1.1.1.dist-info/RECORD
