Metadata-Version: 2.4
Name: bvista
Version: 1.1.1
Summary: B-Vista: A powerful data visualization and exploration tool for pandas DataFrames.
Project-URL: Homepage, https://github.com/Baci-Ak/b-vista
Project-URL: Documentation, https://github.com/Baci-Ak/b-vista/wiki
Project-URL: Source, https://github.com/Baci-Ak/b-vista
Project-URL: Bug-Tracker, https://github.com/Baci-Ak/b-vista/issues
Project-URL: Changelog, https://github.com/Baci-Ak/b-vista/releases
Author-email: Bassey Akom <bassi.cim@gmail.com>
License: BSD-3-Clause
License-File: LICENSE
Keywords: EDA,Python,data-visualization,dataframe,exploratory-analysis,pandas
Classifier: Development Status :: 4 - Beta
Classifier: Intended Audience :: Developers
Classifier: Intended Audience :: Education
Classifier: Intended Audience :: Science/Research
Classifier: License :: OSI Approved :: BSD License
Classifier: Operating System :: OS Independent
Classifier: Programming Language :: Python :: 3
Classifier: Programming Language :: Python :: 3.7
Classifier: Programming Language :: Python :: 3.8
Classifier: Programming Language :: Python :: 3.9
Classifier: Programming Language :: Python :: 3.10
Classifier: Programming Language :: Python :: 3.11
Classifier: Topic :: Education
Classifier: Topic :: Scientific/Engineering :: Visualization
Classifier: Topic :: Software Development :: Libraries :: Python Modules
Requires-Python: >=3.7
Requires-Dist: dcor
Requires-Dist: flask-cors
Requires-Dist: flask-socketio>=5.0.0
Requires-Dist: flask>=2.0.0
Requires-Dist: ipython
Requires-Dist: ipywidgets
Requires-Dist: matplotlib
Requires-Dist: missingno
Requires-Dist: numpy>=1.18
Requires-Dist: pandas>=1.0
Requires-Dist: pingouin
Requires-Dist: plotly
Requires-Dist: pymc
Requires-Dist: requests
Requires-Dist: scikit-learn
Requires-Dist: scipy
Requires-Dist: seaborn
Requires-Dist: statsmodels
